{"protocol":{"minReaderVersion":1,"minWriterVersion":2}}
{"metaData":{"id":"a9eb0f3c-b122-425b-8d54-2a1c0c681c32","name":null,"description":null,"format":{"provider":"parquet","options":{}},"schemaString":"{\"type\":\"struct\",\"fields\":[{\"name\":\"date\",\"type\":\"string\",\"nullable\":false,\"metadata\":{}},{\"name\":\"bcpi_total\",\"type\":\"double\",\"nullable\":true,\"metadata\":{}},{\"name\":\"bcpi_energy\",\"type\":\"double\",\"nullable\":true,\"metadata\":{}},{\"name\":\"bcpi_non_energy\",\"type\":\"double\",\"nullable\":true,\"metadata\":{}}]}","partitionColumns":[],"createdTime":1767332676432,"configuration":{}}}
{"add":{"path":"part-00000-2551faed-0889-4478-a369-dd0e1bd3643b-c000.snappy.parquet","partitionValues":{},"size":8515,"modificationTime":1767332676739,"dataChange":true,"stats":"{\"numRecords\":395,\"minValues\":{\"date\":\"1993-01\",\"bcpi_non_energy\":-26.2,\"bcpi_energy\":-75.5,\"bcpi_total\":-48.8},\"maxValues\":{\"bcpi_non_energy\":62.9,\"date\":\"2025-11\",\"bcpi_total\":141.6,\"bcpi_energy\":308.2},\"nullCount\":{\"bcpi_non_energy\":0,\"bcpi_total\":0,\"date\":0,\"bcpi_energy\":0}}","tags":null,"baseRowId":null,"defaultRowCommitVersion":null,"clusteringProvider":null}}
{"commitInfo":{"timestamp":1767332676739,"operation":"WRITE","operationParameters":{"mode":"ErrorIfExists"},"engineInfo":"delta-rs:py-1.2.1","clientVersion":"delta-rs.py-1.2.1","operationMetrics":{"execution_time_ms":307,"num_added_files":1,"num_added_rows":395,"num_partitions":0,"num_removed_files":0}}}